afragment/__init__.py
afragment/client.py
afragment/exceptions.py
afragment/py.typed
afragment/utils.py
afragment-0.3.0.dist-info/licenses/LICENSE
afragment_test_app/app.py
afragment_test_app/app_easy.py
afragment-0.3.0.dist-info/METADATA
afragment-0.3.0.dist-info/WHEEL
afragment-0.3.0.dist-info/top_level.txt
afragment-0.3.0.dist-info/RECORD
