Metadata-Version: 2.4
Name: afragment
Version: 0.3.0
Summary: Async Python library for Fragment.com API - Purchase Telegram Stars, Premium, and TON topups
Author: TheBrainAir
License: MIT License
Project-URL: Homepage, https://github.com/TheBrainAir/afragment
Project-URL: Documentation, https://github.com/TheBrainAir/afragment#readme
Project-URL: Issues, https://github.com/TheBrainAir/afragment/issues
Keywords: telegram,fragment,stars,premium,ton,async,api
Classifier: Development Status :: 4 - Beta
Classifier: Intended Audience :: Developers
Classifier: License :: OSI Approved :: MIT License
Classifier: Operating System :: OS Independent
Classifier: Programming Language :: Python :: 3
Classifier: Programming Language :: Python :: 3.8
Classifier: Programming Language :: Python :: 3.9
Classifier: Programming Language :: Python :: 3.10
Classifier: Programming Language :: Python :: 3.11
Classifier: Programming Language :: Python :: 3.12
Classifier: Framework :: AsyncIO
Classifier: Topic :: Internet :: WWW/HTTP
Classifier: Topic :: Software Development :: Libraries :: Python Modules
Classifier: Typing :: Typed
Requires-Python: >=3.8
License-File: LICENSE
Requires-Dist: aiohttp>=3.8.0
Provides-Extra: dev
Requires-Dist: pytest>=7.0.0; extra == "dev"
Requires-Dist: pytest-asyncio>=0.21.0; extra == "dev"
Dynamic: license-file
